pypkgs_fatse/__init__.py
pypkgs_fatse/pypkgs_fatse.py
pypkgs_fatse-0.1.0.dist-info/LICENSE
pypkgs_fatse-0.1.0.dist-info/WHEEL
pypkgs_fatse-0.1.0.dist-info/METADATA
pypkgs_fatse-0.1.0.dist-info/RECORD
